{
  "type": "minecraft:crafting_shapeless",
  "ingredients": [
    {
      "item": "cookielicious:sweet_berry_cookie_tiles_vertical_slab"
    }
  ],
  "result": {
    "item": "cookielicious:sweet_berry_cookie_tiles_slab",
    "count": 1
  },
  "conditions": [
    {
      "type": "forge:mod_loaded",
      "modid": "farmersdelight"
    },
    {
      "type": "abnormals_core:quark_flag",
      "flag": "vertical_slabs"
    },
	{
      "type": "differentiate:condition",
      "condition": "sweet_berry_cookie_tiles"
    }
  ]
}